tfrecord_dataset/__init__.py
tfrecord_dataset/iterator_utils.py
tfrecord_dataset/reader.py
tfrecord_dataset/torch.py
tfrecord_dataset/torch_test.py
tfrecord_dataset/writer.py
tfrecord_dataset/tools/__init__.py
tfrecord_dataset/tools/tfrecord2idx.py
tfrecord_dataset-0.2.0.dist-info/LICENSE
tfrecord_dataset-0.2.0.dist-info/METADATA
tfrecord_dataset-0.2.0.dist-info/WHEEL
tfrecord_dataset-0.2.0.dist-info/top_level.txt
tfrecord_dataset-0.2.0.dist-info/RECORD
