Metadata-Version: 2.1
Name: tfrecord_dataset
Version: 0.2.0
Summary: TFRecord reader, writer, and PyTorch Dataset.
Home-page: https://github.com/chaiko/tfrecord_dataset
Author: Ye Jia
Author-email: jiayephy@gmail.com
License: MIT
Requires-Python: >=3.7
License-File: LICENSE
Requires-Dist: numpy
Requires-Dist: crc32c
